odoo/addons/sale_margin_security/README.rst
odoo/addons/sale_margin_security/__init__.py
odoo/addons/sale_margin_security/__manifest__.py
odoo/addons/sale_margin_security/i18n/es.po
odoo/addons/sale_margin_security/i18n/it.po
odoo/addons/sale_margin_security/i18n/sale_margin_security.pot
odoo/addons/sale_margin_security/i18n/tr.po
odoo/addons/sale_margin_security/models/__init__.py
odoo/addons/sale_margin_security/models/sale_order.py
odoo/addons/sale_margin_security/readme/CONFIGURE.md
odoo/addons/sale_margin_security/readme/CONTEXT.md
odoo/addons/sale_margin_security/readme/CONTRIBUTORS.md
odoo/addons/sale_margin_security/readme/DESCRIPTION.md
odoo/addons/sale_margin_security/readme/INSTALL.md
odoo/addons/sale_margin_security/readme/USAGE.md
odoo/addons/sale_margin_security/report/__init__.py
odoo/addons/sale_margin_security/report/sale_report.py
odoo/addons/sale_margin_security/static/description/icon.png
odoo/addons/sale_margin_security/static/description/index.html
odoo/addons/sale_margin_security/tests/__init__.py
odoo/addons/sale_margin_security/tests/test_sale_margin.py
odoo/addons/sale_margin_security/views/sale_margin_security_view.xml
odoo_addon_sale_margin_security-18.0.1.0.0.4.dist-info/METADATA
odoo_addon_sale_margin_security-18.0.1.0.0.4.dist-info/WHEEL
odoo_addon_sale_margin_security-18.0.1.0.0.4.dist-info/top_level.txt
odoo_addon_sale_margin_security-18.0.1.0.0.4.dist-info/RECORD
